{
  "Cuid": 4,
  "Ctime": "2024-07-25 16:05",
  "Cgrade": 4.5,
  "Ccontent": "坐地铁我俩选择在罗家庄下车，从四五七医院 穿过去，这样比较近。出来时候我俩去另外一侧坐公交，走的应该是很多网友说的在居民区里面走，路很窄，都是老房子，下雨路很不好走。刚到古德寺就开始毛毛小雨了。古德寺在一群高楼中间，游人很少，整个寺庙清净。古德寺的特点在于佛殿仿照了缅甸的阿难陀寺建造，很有异域风情。",
  "Cphoto":["https://img1.qunarzz.com/p/tts5/1801/b2/d2cd782be57f1c02.jpg_r_720x480x95_06c23b85.jpg", "https://img1.qunarzz.com/p/tts3/1801/bd/3960d923d9059f02.jpg_r_720x480x95_a6086c20.jpg", "https://img1.qunarzz.com/p/tts8/1801/16/9d2b03a18683b02.jpg_r_720x480x95_447e433a.jpg"],
  "Caname": "古德寺"
}